{"title":"Linux-软硬链接","date":"2018-12-26T12:42:31.000Z","slug":"软硬连接","categories":["Linux"],"updated":"2019-03-15T12:18:07.829Z","content":"<p>软硬链接区别：</p>\n<p>1.使用限制</p>\n<p>硬链接必须是在同一个文件系统下，不能对目录进行链接</p>\n<p>软链接可以跨文件系统 可以对不存在的文件进行链接 可以对目录进行链接</p>\n<p>2..磁盘利用率</p>\n<p>硬链接使用的是同一个i节点，指向同一个数据块，并不会复制文件，所以硬链接是不占用磁盘空间，类似语言中的引用</p>\n<p>软连接文件中存放的被链接的文件路径，两者的i节点不同，占用磁盘很小的空间，有点类似指针，指针的内容是地址</p>\n<p>3.文件删除</p>\n<p>硬链接创建时会增加文件的链接数 只有链接数为0的时候才会删除数据块</p>\n<p>软链接删除源文件（被链接文件），访问链接文件是会出错，因为找不到这个文件路径了</p>\n","prev":{"title":"redis基础","slug":"redis的安装"},"next":{"title":"通过Pycharm操作MySQL","slug":"通过Pycharm操作MySQL"},"link":"http://yoursite.com/post/软硬连接/"}